collective.mailchimp-3.1.1-py3.10-nspkg.pth
collective/mailchimp/__init__.py
collective/mailchimp/configure.zcml
collective/mailchimp/exceptions.py
collective/mailchimp/interfaces.py
collective/mailchimp/locator.py
collective/mailchimp/testing.py
collective/mailchimp/upgrades.py
collective/mailchimp/upgrades.zcml
collective/mailchimp/vocabularies.py
collective/mailchimp/browser/__init__.py
collective/mailchimp/browser/configure.zcml
collective/mailchimp/browser/controlpanel.pt
collective/mailchimp/browser/controlpanel.py
collective/mailchimp/browser/extender.py
collective/mailchimp/browser/extender.zcml
collective/mailchimp/browser/newsletter.py
collective/mailchimp/browser/portlet.pt
collective/mailchimp/browser/portlet.py
collective/mailchimp/browser/z3cformhelpers.py
collective/mailchimp/browser/images/mailchimp.gif
collective/mailchimp/browser/stylesheets/mailchimp.css
collective/mailchimp/locales/collective.mailchimp.pot
collective/mailchimp/locales/de/LC_MESSAGES/collective.mailchimp.po
collective/mailchimp/locales/fr/LC_MESSAGES/collective.mailchimp.po
collective/mailchimp/locales/it/LC_MESSAGES/collective.mailchimp.po
collective/mailchimp/locales/nl/LC_MESSAGES/collective.mailchimp.po
collective/mailchimp/locales/pt_BR/LC_MESSAGES/collective.mailchimp.po
collective/mailchimp/locales/ro/LC_MESSAGES/collective.mailchimp.po
collective/mailchimp/profiles/default/browserlayer.xml
collective/mailchimp/profiles/default/controlpanel.xml
collective/mailchimp/profiles/default/cssregistry.xml
collective/mailchimp/profiles/default/metadata.xml
collective/mailchimp/profiles/default/portlets.xml
collective/mailchimp/profiles/default/registry.xml
collective/mailchimp/profiles/uninstall/browserlayer.xml
collective/mailchimp/profiles/uninstall/controlpanel.xml
collective/mailchimp/profiles/uninstall/registry.xml
collective/mailchimp/tests/__init__.py
collective/mailchimp/tests/test_controlpanel.py
collective/mailchimp/tests/test_exceptions.py
collective.mailchimp-3.1.1.dist-info/METADATA
collective.mailchimp-3.1.1.dist-info/WHEEL
collective.mailchimp-3.1.1.dist-info/entry_points.txt
collective.mailchimp-3.1.1.dist-info/namespace_packages.txt
collective.mailchimp-3.1.1.dist-info/top_level.txt
collective.mailchimp-3.1.1.dist-info/RECORD
