Metadata-Version: 2.1
Name: collective.mailchimp
Version: 3.1.1
Summary: MailChimp integration for Plone.
Home-page: https://pypi.python.org/pypi/collective.mailchimp
Author: kitconcept GmbH (Timo Stollenwerk)
Author-email: stollenwerk@kitconcept.com
License: GPL version 2
Keywords: Python Plone MailChimp Mail Newsletter
Classifier: Environment :: Web Environment
Classifier: Development Status :: 5 - Production/Stable
Classifier: Framework :: Plone
Classifier: Framework :: Plone :: 4.0
Classifier: Framework :: Plone :: 4.1
Classifier: Framework :: Plone :: 4.2
Classifier: Framework :: Plone :: 4.3
Classifier: Framework :: Plone :: 5.0
Classifier: Framework :: Plone :: 5.1
Classifier: Framework :: Plone :: 5.2
Classifier: Programming Language :: Python
Classifier: Programming Language :: Python :: 2.6
Classifier: Programming Language :: Python :: 2.7
Classifier: Programming Language :: Python :: 3.7
Classifier: Framework :: Plone
Classifier: Operating System :: OS Independent
Classifier: License :: OSI Approved :: GNU General Public License v2 (GPLv2)
Requires-Python: >=2.7,!=3.0.*,!=3.1.*,!=3.2.*,!=3.3.*,!=3.4.*,!=3.5.*
Requires-Dist: setuptools
Requires-Dist: Products.CMFPlone
Requires-Dist: plone.app.portlets
Requires-Dist: plone.app.registry
Requires-Dist: plone.app.upgrade
Requires-Dist: requests
Provides-Extra: test
Requires-Dist: mock ; extra == 'test'
Requires-Dist: plone.app.testing ; extra == 'test'
Requires-Dist: plone.api ; extra == 'test'
